pyutil/__init__.py
pyutil/defaults.py
pyutil/ldap.py
pyutil/logger.py
pyutil/mail.py
pyutil/pyutil_mysql.py
pyutil_juposs-2.1.0.dist-info/LICENSE
pyutil_juposs-2.1.0.dist-info/METADATA
pyutil_juposs-2.1.0.dist-info/WHEEL
pyutil_juposs-2.1.0.dist-info/top_level.txt
pyutil_juposs-2.1.0.dist-info/RECORD
