Metadata-Version: 2.1
Name: pyutil-juposs
Version: 2.1.0
Summary: A python utility package
Home-page: https://github.com/juposs/pyutil
Author: Julian Poß
Author-email: pyutil@jposs.de
Project-URL: Bug Tracker, https://github.com/juposs/pyutil/issues
Classifier: Programming Language :: Python :: 3
Classifier: License :: OSI Approved :: MIT License
Classifier: Operating System :: OS Independent
Requires-Python: >=3.6
License-File: LICENSE
Requires-Dist: ldap3
Requires-Dist: logzero
Requires-Dist: mysql-connector-python
